Topsis/__init__.py
Topsis/__main__.py
Topsis_Swasti_102103285-1.0.0.dist-info/LICENSE
Topsis_Swasti_102103285-1.0.0.dist-info/METADATA
Topsis_Swasti_102103285-1.0.0.dist-info/WHEEL
Topsis_Swasti_102103285-1.0.0.dist-info/entry_points.txt
Topsis_Swasti_102103285-1.0.0.dist-info/top_level.txt
Topsis_Swasti_102103285-1.0.0.dist-info/RECORD
