Metadata-Version: 2.1
Name: Topsis-Swasti-102103285
Version: 1.0.0
Summary: Performs TOPSIS
Home-page: https://github.com/sswasti1903/Topsis-Swasti-102103285
Author: Swasti
Author-email: sswasti_be21@thapar.edu
License: MIT
Classifier: License :: OSI Approved :: MIT License
Classifier: Programming Language :: Python :: 3.6
Classifier: Programming Language :: Python :: 3.7
Classifier: Programming Language :: Python :: 3.8
License-File: LICENSE
